{
    "DescrId": "e08bbc77-949b-443f-990f-2b58a02d1198",
    "_id": "34e28818-b566-4e4d-8cca-e46f3014e591",
    "belongTo": null,
    "createInfo": {
        "dateTime": {
            "$date": 1543283992265
        },
        "userId": "6c2edb55-5cb3-4378-9f9c-8e82bdabf60d",
        "userName": "jji"
    },
    "createdBy": "NetBrain",
    "deviceTypes": [
        {
            "_id": 3333,
            "name": "3Com Switch"
        },
        {
            "_id": 10369,
            "name": "A10 Load Balancer"
        },
        {
            "_id": 10352,
            "name": "Adtran"
        },
        {
            "_id": 10586,
            "name": "Adva Optical"
        },
        {
            "_id": 10225,
            "name": "Aerohive Wireless"
        },
        {
            "_id": 10417,
            "name": "Alcatel Lucent Service Router"
        },
        {
            "_id": 10530,
            "name": "Alcatel OmniStack Switch"
        },
        {
            "_id": 10418,
            "name": "Alcatel OmniSwitch"
        },
        {
            "_id": 2013,
            "name": "Arista Switch"
        },
        {
            "_id": 10566,
            "name": "Arris Router"
        },
        {
            "_id": 10547,
            "name": "Aruba IAP"
        },
        {
            "_id": 10529,
            "name": "Aruba LWAP"
        },
        {
            "_id": 11210,
            "name": "Aruba Switch"
        },
        {
            "_id": 3035,
            "name": "Aruba WLC"
        },
        {
            "_id": 10592,
            "name": "Avaya Router"
        },
        {
            "_id": 10513,
            "name": "Avaya Switch"
        },
        {
            "_id": 10659,
            "name": "Avaya VSP"
        },
        {
            "_id": 10930,
            "name": "Big Switch"
        },
        {
            "_id": 10615,
            "name": "Bluecoat"
        },
        {
            "_id": 2024,
            "name": "Brocade Switch"
        },
        {
            "_id": 10533,
            "name": "Brocade Vyatta Router"
        },
        {
            "_id": 3003,
            "name": "Cache Engine"
        },
        {
            "_id": 10624,
            "name": "Calix B-Series"
        },
        {
            "_id": 10567,
            "name": "Calix E-Series"
        },
        {
            "_id": 3001,
            "name": "Call Manager"
        },
        {
            "_id": 10516,
            "name": "Casa"
        },
        {
            "_id": 2007,
            "name": "Checkpoint Firewall"
        },
        {
            "_id": 2140,
            "name": "Ciena Switch"
        },
        {
            "_id": 10357,
            "name": "Cisco ACE"
        },
        {
            "_id": 30001,
            "name": "Cisco ACI APIC"
        },
        {
            "_id": 30003,
            "name": "Cisco ACI Leaf Switch"
        },
        {
            "_id": 30002,
            "name": "Cisco ACI Spine Switch"
        },
        {
            "_id": 2009,
            "name": "Cisco ASA Firewall"
        },
        {
            "_id": 2062,
            "name": "Cisco CSS"
        },
        {
            "_id": 2060,
            "name": "Cisco Catalyst Switch"
        },
        {
            "_id": 2001,
            "name": "Cisco IOS Switch"
        },
        {
            "_id": 2999,
            "name": "Cisco IOS XR"
        },
        {
            "_id": 10617,
            "name": "Cisco MDS"
        },
        {
            "_id": 10571,
            "name": "Cisco Meraki AP"
        },
        {
            "_id": 10613,
            "name": "Cisco Meraki Cloud"
        },
        {
            "_id": 10616,
            "name": "Cisco Meraki Firewall"
        },
        {
            "_id": 10591,
            "name": "Cisco Meraki Switch"
        },
        {
            "_id": 2004,
            "name": "Cisco Nexus Switch"
        },
        {
            "_id": 2002,
            "name": "Cisco PIX Firewall"
        },
        {
            "_id": 2,
            "name": "Cisco Router"
        },
        {
            "_id": 10441,
            "name": "Cisco UCS Fabric"
        },
        {
            "_id": 10563,
            "name": "Cisco VDS"
        },
        {
            "_id": 10532,
            "name": "Cisco WAAS"
        },
        {
            "_id": 1025,
            "name": "Cisco WAP"
        },
        {
            "_id": 3033,
            "name": "Cisco WLC"
        },
        {
            "_id": 10811,
            "name": "Crossbeam Firewall"
        },
        {
            "_id": 2015,
            "name": "Dell Force10 Switch"
        },
        {
            "_id": 10327,
            "name": "Dell Networking Switch"
        },
        {
            "_id": 10515,
            "name": "Dell Sonicwall"
        },
        {
            "_id": 12220,
            "name": "Digi Cellular Router"
        },
        {
            "_id": 10531,
            "name": "Dlink Switch"
        },
        {
            "_id": 1004,
            "name": "End System"
        },
        {
            "_id": 2150,
            "name": "Enterasys Switch"
        },
        {
            "_id": 2023,
            "name": "Extreme Switch"
        },
        {
            "_id": 2003,
            "name": "F5 Load Balancer"
        },
        {
            "_id": 10380,
            "name": "Fortinet FortiGate Firewall"
        },
        {
            "_id": 10618,
            "name": "Fujitsu Switch"
        },
        {
            "_id": 10611,
            "name": "GigaVUE-OS"
        },
        {
            "_id": 2041,
            "name": "HP Menu-Driven Switch"
        },
        {
            "_id": 2011,
            "name": "HP ProCurve Switch"
        },
        {
            "_id": 10416,
            "name": "Hirschmann Switch"
        },
        {
            "_id": 10430,
            "name": "HuaWei Switch"
        },
        {
            "_id": 11232,
            "name": "IBM DataPower"
        },
        {
            "_id": 10660,
            "name": "IBM Switch"
        },
        {
            "_id": 3002,
            "name": "IP Phone"
        },
        {
            "_id": 2012,
            "name": "Juniper EX Switch"
        },
        {
            "_id": 10540,
            "name": "Juniper QFabric System"
        },
        {
            "_id": 102,
            "name": "Juniper Router"
        },
        {
            "_id": 2018,
            "name": "Juniper SRX Firewall"
        },
        {
            "_id": 3034,
            "name": "LWAP"
        },
        {
            "_id": 10455,
            "name": "MRV"
        },
        {
            "_id": 10336,
            "name": "MikroTik"
        },
        {
            "_id": 10921,
            "name": "Moxa Switch"
        },
        {
            "_id": 2008,
            "name": "NetScreen Firewall"
        },
        {
            "_id": 10381,
            "name": "Netscaler Load Balancer"
        },
        {
            "_id": 12225,
            "name": "Nexans GigaSwitch"
        },
        {
            "_id": 2110,
            "name": "Nortel Switch"
        },
        {
            "_id": 10951,
            "name": "Oracle Acme"
        },
        {
            "_id": 2130,
            "name": "Palo Alto Firewall"
        },
        {
            "_id": 10002,
            "name": "Planet WGSW"
        },
        {
            "_id": 10429,
            "name": "Radwin Radio Devices"
        },
        {
            "_id": 10623,
            "name": "Redback Router"
        },
        {
            "_id": 10466,
            "name": "Riverbed WAN Optimizer"
        },
        {
            "_id": 10457,
            "name": "RuggedCom ROX Switch"
        },
        {
            "_id": 10487,
            "name": "RuggedCom RS(G)"
        },
        {
            "_id": 10465,
            "name": "SMC Switch"
        },
        {
            "_id": 10402,
            "name": "Sidewinder Firewall"
        },
        {
            "_id": 10541,
            "name": "SilverPeak WAN Optimizer"
        },
        {
            "_id": 10945,
            "name": "Stonesoft NGFW"
        },
        {
            "_id": 10632,
            "name": "T-Marc 300 Series"
        },
        {
            "_id": 10485,
            "name": "Tellabs Router"
        },
        {
            "_id": 10524,
            "name": "Tellabs Switch"
        },
        {
            "_id": 10920,
            "name": "Ubiquiti airMAX"
        },
        {
            "_id": 1021,
            "name": "Unclassified Device"
        },
        {
            "_id": 2030,
            "name": "Unclassified Firewall"
        },
        {
            "_id": 2035,
            "name": "Unclassified Load Balancer"
        },
        {
            "_id": 2021,
            "name": "Unclassified Router"
        },
        {
            "_id": 2061,
            "name": "Unclassified Switch"
        },
        {
            "_id": 10464,
            "name": "Uplogix"
        },
        {
            "_id": 13002,
            "name": "VM Host"
        },
        {
            "_id": 10619,
            "name": "Viptela"
        },
        {
            "_id": 10950,
            "name": "Watchguard Firewall"
        },
        {
            "_id": 10339,
            "name": "Xirrus Wireless Array"
        },
        {
            "_id": 13004,
            "name": "vSphere Distributed Switch"
        },
        {
            "_id": 13003,
            "name": "vSphere Standard Switch"
        }
    ],
    "links": [
        {
            "category": "noLinkable",
            "from": "e59a97cd-711f-407a-ad3b-337636e042e2",
            "fromPort": "bottom",
            "name": "+ Add Branch Name",
            "points": null,
            "to": "3da19c90-a0f8-49ca-9622-80f6333ac09a",
            "toPort": "top"
        },
        {
            "category": "",
            "from": "516a1ec1-1c89-4375-bb39-a5a6613132d4",
            "fromPort": "bottom",
            "name": "+ Add Branch Name",
            "points": null,
            "to": "6143f01f-68ff-445f-ac3f-c5988cbf114b",
            "toPort": "top"
        },
        {
            "category": "",
            "from": "6143f01f-68ff-445f-ac3f-c5988cbf114b",
            "fromPort": "bottom",
            "name": "+ Add Branch Name",
            "points": null,
            "to": "9ed207dc-a5f5-4442-b67e-ae3c6e5baabb",
            "toPort": "top"
        },
        {
            "category": "",
            "from": "9ed207dc-a5f5-4442-b67e-ae3c6e5baabb",
            "fromPort": "bottom",
            "name": "+ Add Branch Name",
            "points": null,
            "to": "a8556174-fc8e-4b77-a630-72fe7f616bd3",
            "toPort": "top"
        },
        {
            "category": "",
            "from": "a8556174-fc8e-4b77-a630-72fe7f616bd3",
            "fromPort": "bottom",
            "name": "+ Add Branch Name",
            "points": null,
            "to": "e59a97cd-711f-407a-ad3b-337636e042e2",
            "toPort": "top"
        }
    ],
    "nodes": [
        {
            "_id": "3da19c90-a0f8-49ca-9622-80f6333ac09a",
            "bgColor": null,
            "border": null,
            "category": "-2",
            "contextMenuIcon": null,
            "defaultInput": null,
            "icon": null,
            "key": "3da19c90-a0f8-49ca-9622-80f6333ac09a",
            "loc": "7.5 375",
            "maxIndex": 0,
            "name": null,
            "nodeState": 0,
            "type": -2
        },
        {
            "_id": "6143f01f-68ff-445f-ac3f-c5988cbf114b",
            "bgColor": "#feefd6",
            "border": "#f9ae1f",
            "category": null,
            "contextMenuIcon": "run-qapp-16",
            "defaultInput": "{\"option\":{\"dataSource\":{\"type\":1},\"dataViewSetting\":{\"dataViewMapping\":[{\"qappId\":\"6e3717f5-f0a3-f9ae-e910-6b38e94c1596\",\"qappName\":\"Monitor SNMP Packets\",\"qappPath\":\"Built-in Qapps/Monitoring/Monitor SNMP Packets\",\"dataViewGroupName\":\"Monitor SNMP Packets\"}],\"saveAsType\":1},\"runQappModel\":1,\"dataFolderToRun\":{\"dataFolderId\":\"0\"},\"shareAlertUser\":[]},\"qappList\":[{\"isGenerateDataView\":true,\"qappId\":\"6e3717f5-f0a3-f9ae-e910-6b38e94c1596\",\"qappName\":\"Monitor SNMP Packets\",\"qappPath\":\"Built-in Qapps/Monitoring/Monitor SNMP Packets\",\"runOption\":{\"type\":2,\"times\":10,\"interval\":{\"unit\":2,\"duration\":2}},\"tableInput\":[],\"isReportDrawPath\":false,\"threshold\":{\"monItems\":\"{\\\"SNMPTable\\\":{\\\"Guid\\\":\\\"ba30b7f2-96ff-b491-ce58-e49fdcbed1ea\\\",\\\"MonItemPos\\\":0,\\\"MonItemType\\\":1,\\\"Sequence\\\":0,\\\"ValueType\\\":11,\\\"ValueUnit\\\":\\\"\\\",\\\"allAnalysis\\\":null,\\\"isCompoundCondition\\\":false,\\\"tableName\\\":\\\"SNMPCanvas.SNMPTable\\\"}}\",\"varHtml\":\"<ul class=\\\"Conditon\\\">\\n<li>Monitor SNMP Packets<ul class=\\\"analysis\\\"></ul></li></ul>\\n\"}}],\"name\":\"Monitor SNMP Packets\"}",
            "icon": "action_node_qapp_24",
            "key": "6143f01f-68ff-445f-ac3f-c5988cbf114b",
            "loc": "0 75",
            "maxIndex": 0,
            "name": "1. Monitor SNMP Packets",
            "nodeState": 0,
            "type": 1
        },
        {
            "_id": "9ed207dc-a5f5-4442-b67e-ae3c6e5baabb",
            "bgColor": "#feefd6",
            "border": "#f9ae1f",
            "category": null,
            "contextMenuIcon": "run-qapp-16",
            "defaultInput": "{\"option\":{\"dataSource\":{\"type\":1},\"dataViewSetting\":{\"dataViewMapping\":[{\"qappId\":\"8657c426-9310-a523-ccd1-67fdd8a7e36e\",\"qappName\":\"Highlight SNMP Group Version\",\"qappPath\":\"Built-in Qapps/Highlighting/Highlight SNMP Group Version\",\"dataViewGroupName\":\"Highlight SNMP Group Version\"}],\"saveAsType\":1},\"runQappModel\":1,\"dataFolderToRun\":{\"dataFolderId\":\"0\"},\"shareAlertUser\":[]},\"qappList\":[{\"isGenerateDataView\":true,\"qappId\":\"8657c426-9310-a523-ccd1-67fdd8a7e36e\",\"qappName\":\"Highlight SNMP Group Version\",\"qappPath\":\"Built-in Qapps/Highlighting/Highlight SNMP Group Version\",\"runOption\":{\"type\":1},\"tableInput\":[],\"isReportDrawPath\":false,\"threshold\":{\"monItems\":\"null\",\"varHtml\":\"<ul class=\\\"Conditon\\\">\\n<li>Highlight SNMP Group Version<ul class=\\\"analysis\\\"></ul></li></ul>\\n\"}}],\"name\":\"Highlight SNMP Group Version\"}",
            "icon": "action_node_qapp_24",
            "key": "9ed207dc-a5f5-4442-b67e-ae3c6e5baabb",
            "loc": "0 150",
            "maxIndex": 0,
            "name": "2. Highlight SNMP Group Version",
            "nodeState": 0,
            "type": 1
        },
        {
            "_id": "a8556174-fc8e-4b77-a630-72fe7f616bd3",
            "bgColor": "#feefd6",
            "border": "#f9ae1f",
            "category": null,
            "contextMenuIcon": "panel_qapp_group",
            "defaultInput": "{\"gappId\":\"722af97e-fbdc-690b-6b0d-48c0488ba1f7\",\"gappPath\":\"Built-in Gapps/Highlighting/Highlight SNMP Community and ACL\",\"dataSource\":{\"type\":1},\"frequency\":{\"type\":1},\"thresholds\":[],\"tableInputs\":[{\"qappNodeId\":\"8\",\"tableInput\":[{\"name\":\"InputSnmpServer\",\"allowEditAtRuntime\":true,\"columns\":[],\"rows\":[],\"attributes\":[{\"name\":\"snmp_community\",\"type\":4,\"default\":\"private, public\",\"value\":\"private, public\",\"purpose\":\"Original\",\"script\":\"\"}]}]},{\"qappNodeId\":\"9\",\"tableInput\":[]}],\"isReportDrawPath\":false,\"isGenerateDataView\":true,\"dataViewSetting\":{\"dataViewMapping\":[{\"qappId\":\"4c332f14-83e1-9b9c-7e44-f2e55366d235\",\"qappName\":\"Highlight SNMP Community\",\"qappPath\":\"Built-in Qapps/Highlighting/Highlight SNMP Community\",\"gappNodeId\":\"8\",\"dataViewGroupName\":\"Highlight SNMP Community\"},{\"qappId\":\"355ee862-a1f3-8457-9e3a-8f3a65e7f26a\",\"qappName\":\"Highlight Specified ACL\",\"qappPath\":\"Built-in Qapps/Highlighting/Highlight Specified ACL\",\"gappNodeId\":\"9\",\"dataViewGroupName\":\"Highlight Specified ACL\"}],\"saveAsType\":1},\"pathTemplateId\":\"\",\"runModel\":1,\"name\":\"Highlight SNMP Community and ACL\"}",
            "icon": "action_node_qapp_group_24",
            "key": "a8556174-fc8e-4b77-a630-72fe7f616bd3",
            "loc": "0 225",
            "maxIndex": 0,
            "name": "3. Highlight SNMP Community and ACL",
            "nodeState": 0,
            "type": 30
        },
        {
            "_id": "e59a97cd-711f-407a-ad3b-337636e042e2",
            "bgColor": "#feefd6",
            "border": "#f9ae1f",
            "category": null,
            "contextMenuIcon": "run-qapp-16",
            "defaultInput": "{\"option\":{\"dataSource\":{\"type\":1},\"dataViewSetting\":{\"dataViewMapping\":[{\"qappId\":\"530642bf-0f33-90d3-cf0f-86f0b4b076f4\",\"qappName\":\"Highlight SNMP Traps\",\"qappPath\":\"Built-in Qapps/Highlighting/Highlight SNMP Traps\",\"dataViewGroupName\":\"Highlight SNMP Traps\"}],\"saveAsType\":1},\"runQappModel\":1,\"dataFolderToRun\":{\"dataFolderId\":\"0\"},\"shareAlertUser\":[]},\"qappList\":[{\"isGenerateDataView\":true,\"qappId\":\"530642bf-0f33-90d3-cf0f-86f0b4b076f4\",\"qappName\":\"Highlight SNMP Traps\",\"qappPath\":\"Built-in Qapps/Highlighting/Highlight SNMP Traps\",\"runOption\":{\"type\":1},\"tableInput\":[],\"isReportDrawPath\":false,\"threshold\":{\"monItems\":\"null\",\"varHtml\":\"<ul class=\\\"Conditon\\\">\\n<li>Highlight SNMP Traps<ul class=\\\"analysis\\\"></ul></li></ul>\\n\"}}],\"name\":\"Highlight SNMP Traps\"}",
            "icon": "action_node_qapp_24",
            "key": "e59a97cd-711f-407a-ad3b-337636e042e2",
            "loc": "0 300",
            "maxIndex": 0,
            "name": "4. Highlight SNMP Traps",
            "nodeState": 0,
            "type": 1
        },
        {
            "_id": "516a1ec1-1c89-4375-bb39-a5a6613132d4",
            "bgColor": null,
            "border": null,
            "category": "-1",
            "contextMenuIcon": null,
            "defaultInput": null,
            "icon": null,
            "key": "516a1ec1-1c89-4375-bb39-a5a6613132d4",
            "loc": "0 0",
            "maxIndex": 0,
            "name": "Runbook Info",
            "nodeState": 0,
            "type": -1
        }
    ],
    "rbType": 1,
    "rb_notes": [
        {
            "_id": "d6ea8457-4b33-4392-b6ae-3d274b31619a",
            "_t": "RunbookNote",
            "creatorUser": null,
            "editor": "{\"ops\":[{\"insert\":\"\\nSNMP is an application-layer protocol that provides a message format for communication between SNMP managers and agents. SNMP provides a standardized framework and a common language used for the monitoring and management of devices in a network.\\n \\n1. This Runbook will display SNMP information in detail \\n2. Displaying SNMP group version\\n3. Displaying SNMP community and its related ACL information\\n4. Displaying SNMP Traps information\\n \\nReferences:\\n\"},{\"attributes\":{\"link\":\"http://www.cisco.com/c/en/us/td/docs/ios/12_2/configfun/configuration/guide/ffun_c/fcf014.html\"},\"insert\":\"SNMP Information\"},{\"insert\":\"\\n\"}]}",
            "nodeId": "516a1ec1-1c89-4375-bb39-a5a6613132d4",
            "nodeName": "Runbook Info",
            "operateInfo": null,
            "runBookId": "34e28818-b566-4e4d-8cca-e46f3014e591",
            "text": "\nSNMP is an application-layer protocol that provides a message format for communication between SNMP managers and agents. SNMP provides a standardized framework and a common language used for the monitoring and management of devices in a network.\n \n1. This Runbook will display SNMP information in detail \n2. Displaying SNMP group version\n3. Displaying SNMP community and its related ACL information\n4. Displaying SNMP Traps information\n \nReferences:\nSNMP Information\n",
            "type": 0
        },
        {
            "_id": "99a71912-b0a2-405c-baa7-214d1556d589",
            "_t": "RunbookNote",
            "creatorUser": null,
            "editor": "{\"ops\":[{\"insert\":\"Monitor device SNMP status, it includes input packets and output packets.\\n\\n\"},{\"attributes\":{\"color\":\"#0066cc\"},\"insert\":\"Output:\"},{\"insert\":\"\\n\\t\\tData unit items on device level:\\n\\t\\t\\t1) SNMP Table\\n\"}]}",
            "nodeId": "6143f01f-68ff-445f-ac3f-c5988cbf114b",
            "nodeName": "1. Monitor SNMP Packets",
            "operateInfo": null,
            "runBookId": "34e28818-b566-4e4d-8cca-e46f3014e591",
            "text": "Monitor device SNMP status, it includes input packets and output packets.\n\nOutput:\n\t\tData unit items on device level:\n\t\t\t1) SNMP Table\n",
            "type": 0
        },
        {
            "_id": "c8499fd0-8930-4639-ba21-aea51f495277",
            "_t": "RunbookNote",
            "creatorUser": null,
            "editor": "{\"ops\":[{\"insert\":\"Highlight device when device enable SNMP, and highlight device and draw device note about SNMP group when SNMP is enable.\\n\\n\"},{\"attributes\":{\"color\":\"#0066cc\"},\"insert\":\"Output:\"},{\"insert\":\"\\n\\t\\tHighlight items on device level:\\n\\t\\t\\t1) SNMP Security Model\\n\\n\\t\\tDraw notes on device level:\\n\\t\\t\\t1) SNMP Group\\n\"}]}",
            "nodeId": "9ed207dc-a5f5-4442-b67e-ae3c6e5baabb",
            "nodeName": "2. Highlight SNMP Group Version",
            "operateInfo": null,
            "runBookId": "34e28818-b566-4e4d-8cca-e46f3014e591",
            "text": "Highlight device when device enable SNMP, and highlight device and draw device note about SNMP group when SNMP is enable.\n\nOutput:\n\t\tHighlight items on device level:\n\t\t\t1) SNMP Security Model\n\n\t\tDraw notes on device level:\n\t\t\t1) SNMP Group\n",
            "type": 0
        },
        {
            "_id": "165d17c4-c7a7-4047-9ff1-28b913608374",
            "_t": "RunbookNote",
            "creatorUser": null,
            "editor": "{\"ops\":[{\"insert\":\"Highlight device when a ACL apply to change SNMP community, and a device note will be display in map about community information .\\n\\n\"},{\"attributes\":{\"color\":\"#0066cc\"},\"insert\":\"Input:\"},{\"insert\":\"\\nThe string of SNMP community \"},{\"attributes\":{\"color\":\"#888888\"},\"insert\":\"(for example: private, public)\"},{\"attributes\":{\"list\":\"bullet\"},\"insert\":\"\\n\"},{\"insert\":\"\\n\"},{\"attributes\":{\"color\":\"#0066cc\"},\"insert\":\"Output:\"},{\"insert\":\"\\n\\t\\tHighlight items on device level:\\n\\t\\t\\t1) Safe Community String \"},{\"attributes\":{\"color\":\"#888888\"},\"insert\":\"(color: green)\"},{\"insert\":\"\\n\\t\\t\\t2) Unsafe Community String \"},{\"attributes\":{\"color\":\"#888888\"},\"insert\":\"(color: red)\"},{\"insert\":\"\\n\\n\\t\\tAlert items on device level:\\n\\t\\t\\t1) SNMP Community too Simple \"},{\"attributes\":{\"color\":\"#888888\"},\"insert\":\"(condition: if input SNMP community has been found)\"},{\"insert\":\"\\n\"}]}",
            "nodeId": "a8556174-fc8e-4b77-a630-72fe7f616bd3",
            "nodeName": "Highlight SNMP Community and ACL",
            "operateInfo": null,
            "runBookId": "34e28818-b566-4e4d-8cca-e46f3014e591",
            "text": "Highlight device when a ACL apply to change SNMP community, and a device note will be display in map about community information .\n\nInput:\nThe string of SNMP community (for example: private, public)\n\nOutput:\n\t\tHighlight items on device level:\n\t\t\t1) Safe Community String (color: green)\n\t\t\t2) Unsafe Community String (color: red)\n\n\t\tAlert items on device level:\n\t\t\t1) SNMP Community too Simple (condition: if input SNMP community has been found)\n",
            "type": 0
        },
        {
            "_id": "53418707-8df3-49ad-bd9d-393d57384f1f",
            "_t": "RunbookNote",
            "creatorUser": null,
            "editor": "{\"ops\":[{\"insert\":\"Highlight device when SNMP traps enable and SNMP traps related information will be displayed in device note.\\n\\n\"},{\"attributes\":{\"color\":\"#0066cc\"},\"insert\":\"Output:\"},{\"insert\":\"\\n\\t\\tHighlight items on device level:\\n\\t\\t\\t1) SNMP Traps Device\\n\\t\\n\\t\\tDraw notes on device level:\\n\\t\\t\\t1) SNMP Traps Host\\n\"}]}",
            "nodeId": "e59a97cd-711f-407a-ad3b-337636e042e2",
            "nodeName": "4. Highlight SNMP Traps",
            "operateInfo": null,
            "runBookId": "34e28818-b566-4e4d-8cca-e46f3014e591",
            "text": "Highlight device when SNMP traps enable and SNMP traps related information will be displayed in device note.\n\nOutput:\n\t\tHighlight items on device level:\n\t\t\t1) SNMP Traps Device\n\t\n\t\tDraw notes on device level:\n\t\t\t1) SNMP Traps Host\n",
            "type": 0
        }
    ],
    "tags": [
        "SNMP"
    ],
    "type": 1
}