{
    "_id": "f9a69d51-caaa-4eb8-a357-79e6abbc9ba8",
    "children": [
        {
            "_id": "8e033327-6359-42bc-b6c5-881e28bd311c",
            "children": [
                {
                    "_id": "b906dfd7-6fce-444f-aeb3-0b2e5926494e",
                    "children": [],
                    "command": "show routing protocol bgp summary",
                    "desc": null,
                    "isIntfKey": false,
                    "mapping": {
                        "_id": "9c9b7d91-cd0e-4b4f-a374-ae422d9a86ab",
                        "mappingType": 2,
                        "mappingVars": [
                            {
                                "bizType": "CLI",
                                "builtIn": false,
                                "deviceType": [
                                    2130
                                ],
                                "isKey": false,
                                "parserName": "show routing protocol bgp summary [Palo Alto Firewall]",
                                "parserPath": "Built-in Files/Network Vendors/Palo Alto/Palo Alto Firewall/show routing protocol bgp summary [Palo Alto Firewall]",
                                "sourceType": 1,
                                "varFullName": "bgp_summary.$router_id",
                                "varName": "$router_id"
                            }
                        ]
                    },
                    "mappingType": 2,
                    "name": "$router_id",
                    "nodeType": 4,
                    "params": [],
                    "rules": null,
                    "valueType": 0
                },
                {
                    "_id": "73eb4c43-c457-4016-a67b-7a1831873d8a",
                    "children": [],
                    "command": "show routing protocol bgp summary",
                    "desc": null,
                    "isIntfKey": false,
                    "mapping": {
                        "_id": "e90e11fc-b838-4022-86d7-b36889c8ece0",
                        "mappingType": 2,
                        "mappingVars": [
                            {
                                "bizType": "CLI",
                                "builtIn": false,
                                "deviceType": [
                                    2130
                                ],
                                "isKey": false,
                                "parserName": "show routing protocol bgp summary [Palo Alto Firewall]",
                                "parserPath": "Built-in Files/Network Vendors/Palo Alto/Palo Alto Firewall/show routing protocol bgp summary [Palo Alto Firewall]",
                                "sourceType": 1,
                                "varFullName": "bgp_summary.$virtual_router",
                                "varName": "$virtual_router"
                            }
                        ]
                    },
                    "mappingType": 2,
                    "name": "$virtual_router",
                    "nodeType": 4,
                    "params": [],
                    "rules": null,
                    "valueType": 0
                },
                {
                    "_id": "8f1f0015-2561-447f-86e9-9839a371d8af",
                    "children": [],
                    "command": "show routing protocol bgp summary",
                    "desc": null,
                    "isIntfKey": false,
                    "mapping": {
                        "_id": "75a581ea-2bb6-4c08-bf54-dbf4b1f75914",
                        "mappingType": 2,
                        "mappingVars": [
                            {
                                "bizType": "CLI",
                                "builtIn": false,
                                "deviceType": [
                                    2130
                                ],
                                "isKey": false,
                                "parserName": "show routing protocol bgp summary [Palo Alto Firewall]",
                                "parserPath": "Built-in Files/Network Vendors/Palo Alto/Palo Alto Firewall/show routing protocol bgp summary [Palo Alto Firewall]",
                                "sourceType": 1,
                                "varFullName": "bgp_summary.$reject_default_route",
                                "varName": "$reject_default_route"
                            }
                        ]
                    },
                    "mappingType": 2,
                    "name": "$reject_default_route",
                    "nodeType": 4,
                    "params": [],
                    "rules": null,
                    "valueType": 0
                },
                {
                    "_id": "d5e428a2-b13e-49ed-9bd5-06a345990168",
                    "children": [],
                    "command": "show routing protocol bgp summary",
                    "desc": null,
                    "isIntfKey": false,
                    "mapping": {
                        "_id": "f1dcf07d-a7e1-48ff-8460-e74191b3be3c",
                        "mappingType": 2,
                        "mappingVars": [
                            {
                                "bizType": "CLI",
                                "builtIn": false,
                                "deviceType": [
                                    2130
                                ],
                                "isKey": false,
                                "parserName": "show routing protocol bgp summary [Palo Alto Firewall]",
                                "parserPath": "Built-in Files/Network Vendors/Palo Alto/Palo Alto Firewall/show routing protocol bgp summary [Palo Alto Firewall]",
                                "sourceType": 1,
                                "varFullName": "bgp_summary.$redist_default_route",
                                "varName": "$redist_default_route"
                            }
                        ]
                    },
                    "mappingType": 2,
                    "name": "$redist_default_route",
                    "nodeType": 4,
                    "params": [],
                    "rules": null,
                    "valueType": 0
                },
                {
                    "_id": "9f91efb0-3b3d-4438-9022-ab53a1c832e0",
                    "children": [],
                    "command": "show routing protocol bgp summary",
                    "desc": null,
                    "isIntfKey": false,
                    "mapping": {
                        "_id": "acb1d466-adeb-4145-835e-001201057c1d",
                        "mappingType": 2,
                        "mappingVars": [
                            {
                                "bizType": "CLI",
                                "builtIn": false,
                                "deviceType": [
                                    2130
                                ],
                                "isKey": false,
                                "parserName": "show routing protocol bgp summary [Palo Alto Firewall]",
                                "parserPath": "Built-in Files/Network Vendors/Palo Alto/Palo Alto Firewall/show routing protocol bgp summary [Palo Alto Firewall]",
                                "sourceType": 1,
                                "varFullName": "bgp_summary.$install_bgp_routes",
                                "varName": "$install_bgp_routes"
                            }
                        ]
                    },
                    "mappingType": 2,
                    "name": "$install_bgp_routes",
                    "nodeType": 4,
                    "params": [],
                    "rules": null,
                    "valueType": 0
                },
                {
                    "_id": "1d228d45-15cf-43f0-a1bd-fc6f294afa27",
                    "children": [],
                    "command": "show routing protocol bgp summary",
                    "desc": null,
                    "isIntfKey": false,
                    "mapping": {
                        "_id": "426717ed-d1f4-4eff-985c-fabb31775641",
                        "mappingType": 2,
                        "mappingVars": [
                            {
                                "bizType": "CLI",
                                "builtIn": false,
                                "deviceType": [
                                    2130
                                ],
                                "isKey": false,
                                "parserName": "show routing protocol bgp summary [Palo Alto Firewall]",
                                "parserPath": "Built-in Files/Network Vendors/Palo Alto/Palo Alto Firewall/show routing protocol bgp summary [Palo Alto Firewall]",
                                "sourceType": 1,
                                "varFullName": "bgp_summary.$graceful_restart",
                                "varName": "$graceful_restart"
                            }
                        ]
                    },
                    "mappingType": 2,
                    "name": "$graceful_restart",
                    "nodeType": 4,
                    "params": [],
                    "rules": null,
                    "valueType": 0
                },
                {
                    "_id": "e12e9fc2-b7d6-427d-b42e-e0d88b85e7a4",
                    "children": [],
                    "command": "show routing protocol bgp summary",
                    "desc": null,
                    "isIntfKey": false,
                    "mapping": {
                        "_id": "b0382304-6504-4bc2-98d4-b1fc699c126a",
                        "mappingType": 2,
                        "mappingVars": [
                            {
                                "bizType": "CLI",
                                "builtIn": false,
                                "deviceType": [
                                    2130
                                ],
                                "isKey": false,
                                "parserName": "show routing protocol bgp summary [Palo Alto Firewall]",
                                "parserPath": "Built-in Files/Network Vendors/Palo Alto/Palo Alto Firewall/show routing protocol bgp summary [Palo Alto Firewall]",
                                "sourceType": 1,
                                "varFullName": "bgp_summary.$as_size",
                                "varName": "$as_size"
                            }
                        ]
                    },
                    "mappingType": 2,
                    "name": "$as_size",
                    "nodeType": 4,
                    "params": [],
                    "rules": null,
                    "valueType": 0
                },
                {
                    "_id": "208382d2-57f9-4ba8-bd15-91252292ba6b",
                    "children": [],
                    "command": "show routing protocol bgp summary",
                    "desc": null,
                    "isIntfKey": false,
                    "mapping": {
                        "_id": "76719327-c00d-48fd-a842-72cb1d3b7980",
                        "mappingType": 2,
                        "mappingVars": [
                            {
                                "bizType": "CLI",
                                "builtIn": false,
                                "deviceType": [
                                    2130
                                ],
                                "isKey": false,
                                "parserName": "show routing protocol bgp summary [Palo Alto Firewall]",
                                "parserPath": "Built-in Files/Network Vendors/Palo Alto/Palo Alto Firewall/show routing protocol bgp summary [Palo Alto Firewall]",
                                "sourceType": 1,
                                "varFullName": "bgp_summary.$local_as",
                                "varName": "$local_as"
                            }
                        ]
                    },
                    "mappingType": 2,
                    "name": "$local_as",
                    "nodeType": 4,
                    "params": [],
                    "rules": null,
                    "valueType": 0
                },
                {
                    "_id": "4a253c48-18b2-4301-967d-c321bfb280af",
                    "children": [],
                    "command": "show routing protocol bgp summary",
                    "desc": null,
                    "isIntfKey": false,
                    "mapping": {
                        "_id": "ffb3b2a8-6146-4a88-9f3d-e469a271117f",
                        "mappingType": 2,
                        "mappingVars": [
                            {
                                "bizType": "CLI",
                                "builtIn": false,
                                "deviceType": [
                                    2130
                                ],
                                "isKey": false,
                                "parserName": "show routing protocol bgp summary [Palo Alto Firewall]",
                                "parserPath": "Built-in Files/Network Vendors/Palo Alto/Palo Alto Firewall/show routing protocol bgp summary [Palo Alto Firewall]",
                                "sourceType": 1,
                                "varFullName": "bgp_summary.$local_member_as",
                                "varName": "$local_member_as"
                            }
                        ]
                    },
                    "mappingType": 2,
                    "name": "$local_member_as",
                    "nodeType": 4,
                    "params": [],
                    "rules": null,
                    "valueType": 0
                },
                {
                    "_id": "98747546-f6c6-4e59-9fc4-a9b5c7f0b92a",
                    "children": [],
                    "command": "show routing protocol bgp summary",
                    "desc": null,
                    "isIntfKey": false,
                    "mapping": {
                        "_id": "66d4273d-1bd2-4fab-94ef-aff42a68528b",
                        "mappingType": 2,
                        "mappingVars": [
                            {
                                "bizType": "CLI",
                                "builtIn": false,
                                "deviceType": [
                                    2130
                                ],
                                "isKey": false,
                                "parserName": "show routing protocol bgp summary [Palo Alto Firewall]",
                                "parserPath": "Built-in Files/Network Vendors/Palo Alto/Palo Alto Firewall/show routing protocol bgp summary [Palo Alto Firewall]",
                                "sourceType": 1,
                                "varFullName": "bgp_summary.$cluster_id",
                                "varName": "$cluster_id"
                            }
                        ]
                    },
                    "mappingType": 2,
                    "name": "$cluster_id",
                    "nodeType": 4,
                    "params": [],
                    "rules": null,
                    "valueType": 0
                },
                {
                    "_id": "d110eeaf-b028-42d2-ad19-d15dba0b5429",
                    "children": [],
                    "command": "show routing protocol bgp summary",
                    "desc": null,
                    "isIntfKey": false,
                    "mapping": {
                        "_id": "c41e3bd7-b30f-4e5a-99a9-c52750298993",
                        "mappingType": 2,
                        "mappingVars": [
                            {
                                "bizType": "CLI",
                                "builtIn": false,
                                "deviceType": [
                                    2130
                                ],
                                "isKey": false,
                                "parserName": "show routing protocol bgp summary [Palo Alto Firewall]",
                                "parserPath": "Built-in Files/Network Vendors/Palo Alto/Palo Alto Firewall/show routing protocol bgp summary [Palo Alto Firewall]",
                                "sourceType": 1,
                                "varFullName": "bgp_summary.$default_local_preference",
                                "varName": "$default_local_preference"
                            }
                        ]
                    },
                    "mappingType": 2,
                    "name": "$default_local_preference",
                    "nodeType": 4,
                    "params": [],
                    "rules": null,
                    "valueType": 0
                },
                {
                    "_id": "fb3631e9-922d-4799-a0c3-a559cb92e23d",
                    "children": [],
                    "command": "show routing protocol bgp summary",
                    "desc": null,
                    "isIntfKey": false,
                    "mapping": {
                        "_id": "c5bb4022-d25f-4e86-a4de-b68e2781e584",
                        "mappingType": 2,
                        "mappingVars": [
                            {
                                "bizType": "CLI",
                                "builtIn": false,
                                "deviceType": [
                                    2130
                                ],
                                "isKey": false,
                                "parserName": "show routing protocol bgp summary [Palo Alto Firewall]",
                                "parserPath": "Built-in Files/Network Vendors/Palo Alto/Palo Alto Firewall/show routing protocol bgp summary [Palo Alto Firewall]",
                                "sourceType": 1,
                                "varFullName": "bgp_summary.$always_compare_med",
                                "varName": "$always_compare_med"
                            }
                        ]
                    },
                    "mappingType": 2,
                    "name": "$always_compare_med",
                    "nodeType": 4,
                    "params": [],
                    "rules": null,
                    "valueType": 0
                },
                {
                    "_id": "2f8b214a-000b-4aa6-b86d-32c1a2ff2cc2",
                    "children": [],
                    "command": "show routing protocol bgp summary",
                    "desc": null,
                    "isIntfKey": false,
                    "mapping": {
                        "_id": "3391d31e-b02a-4106-9d1e-cccf9fcf63b3",
                        "mappingType": 2,
                        "mappingVars": [
                            {
                                "bizType": "CLI",
                                "builtIn": false,
                                "deviceType": [
                                    2130
                                ],
                                "isKey": false,
                                "parserName": "show routing protocol bgp summary [Palo Alto Firewall]",
                                "parserPath": "Built-in Files/Network Vendors/Palo Alto/Palo Alto Firewall/show routing protocol bgp summary [Palo Alto Firewall]",
                                "sourceType": 1,
                                "varFullName": "bgp_summary.$aggregate_regardless_med",
                                "varName": "$aggregate_regardless_med"
                            }
                        ]
                    },
                    "mappingType": 2,
                    "name": "$aggregate_regardless_med",
                    "nodeType": 4,
                    "params": [],
                    "rules": null,
                    "valueType": 0
                },
                {
                    "_id": "7933d1ab-c63f-476d-9e2f-a29814c9ed16",
                    "children": [],
                    "command": "show routing protocol bgp summary",
                    "desc": null,
                    "isIntfKey": false,
                    "mapping": {
                        "_id": "4f280879-2cae-48b2-999b-b9e5f4875266",
                        "mappingType": 2,
                        "mappingVars": [
                            {
                                "bizType": "CLI",
                                "builtIn": false,
                                "deviceType": [
                                    2130
                                ],
                                "isKey": false,
                                "parserName": "show routing protocol bgp summary [Palo Alto Firewall]",
                                "parserPath": "Built-in Files/Network Vendors/Palo Alto/Palo Alto Firewall/show routing protocol bgp summary [Palo Alto Firewall]",
                                "sourceType": 1,
                                "varFullName": "bgp_summary.$deterministic_med_processing",
                                "varName": "$deterministic_med_processing"
                            }
                        ]
                    },
                    "mappingType": 2,
                    "name": "$deterministic_med_processing",
                    "nodeType": 4,
                    "params": [],
                    "rules": null,
                    "valueType": 0
                },
                {
                    "_id": "a8387717-176c-4710-a0c4-485c4a41f53e",
                    "children": [],
                    "command": "show routing protocol bgp summary",
                    "desc": null,
                    "isIntfKey": false,
                    "mapping": {
                        "_id": "d1cd5b21-8acb-49a1-97b6-b0a2f2303ab0",
                        "mappingType": 2,
                        "mappingVars": [
                            {
                                "bizType": "CLI",
                                "builtIn": false,
                                "deviceType": [
                                    2130
                                ],
                                "isKey": false,
                                "parserName": "show routing protocol bgp summary [Palo Alto Firewall]",
                                "parserPath": "Built-in Files/Network Vendors/Palo Alto/Palo Alto Firewall/show routing protocol bgp summary [Palo Alto Firewall]",
                                "sourceType": 1,
                                "varFullName": "bgp_summary.$accept_orf",
                                "varName": "$accept_orf"
                            }
                        ]
                    },
                    "mappingType": 2,
                    "name": "$accept_orf",
                    "nodeType": 4,
                    "params": [],
                    "rules": null,
                    "valueType": 0
                },
                {
                    "_id": "3e5da1db-e984-4e38-b710-3ecff6881641",
                    "children": [],
                    "command": "show routing protocol bgp summary",
                    "desc": null,
                    "isIntfKey": false,
                    "mapping": {
                        "_id": "c2649000-f536-4b7e-ae23-647f9463bb2b",
                        "mappingType": 2,
                        "mappingVars": [
                            {
                                "bizType": "CLI",
                                "builtIn": false,
                                "deviceType": [
                                    2130
                                ],
                                "isKey": false,
                                "parserName": "show routing protocol bgp summary [Palo Alto Firewall]",
                                "parserPath": "Built-in Files/Network Vendors/Palo Alto/Palo Alto Firewall/show routing protocol bgp summary [Palo Alto Firewall]",
                                "sourceType": 1,
                                "varFullName": "bgp_summary.$accept_cisco_style_prefix",
                                "varName": "$accept_cisco_style_prefix"
                            }
                        ]
                    },
                    "mappingType": 2,
                    "name": "$accept_cisco_style_prefix",
                    "nodeType": 4,
                    "params": [],
                    "rules": null,
                    "valueType": 0
                },
                {
                    "_id": "fb2b532c-3087-4f42-83ca-9ea32d569b35",
                    "children": [],
                    "command": "show routing protocol bgp summary",
                    "desc": null,
                    "isIntfKey": false,
                    "mapping": {
                        "_id": "c8361b8a-975c-4302-a506-12415f5961cc",
                        "mappingType": 2,
                        "mappingVars": [
                            {
                                "bizType": "CLI",
                                "builtIn": false,
                                "deviceType": [
                                    2130
                                ],
                                "isKey": false,
                                "parserName": "show routing protocol bgp summary [Palo Alto Firewall]",
                                "parserPath": "Built-in Files/Network Vendors/Palo Alto/Palo Alto Firewall/show routing protocol bgp summary [Palo Alto Firewall]",
                                "sourceType": 1,
                                "varFullName": "bgp_summary.$current_rib_out_entries",
                                "varName": "$current_rib_out_entries"
                            }
                        ]
                    },
                    "mappingType": 2,
                    "name": "$current_rib_out_entries",
                    "nodeType": 4,
                    "params": [],
                    "rules": null,
                    "valueType": 0
                },
                {
                    "_id": "bbc225bd-c2c9-489b-9a96-71cecaf34329",
                    "children": [],
                    "command": "show routing protocol bgp summary",
                    "desc": null,
                    "isIntfKey": false,
                    "mapping": {
                        "_id": "77c10a9b-1bf9-41e3-88b8-5560a056b833",
                        "mappingType": 2,
                        "mappingVars": [
                            {
                                "bizType": "CLI",
                                "builtIn": false,
                                "deviceType": [
                                    2130
                                ],
                                "isKey": false,
                                "parserName": "show routing protocol bgp summary [Palo Alto Firewall]",
                                "parserPath": "Built-in Files/Network Vendors/Palo Alto/Palo Alto Firewall/show routing protocol bgp summary [Palo Alto Firewall]",
                                "sourceType": 1,
                                "varFullName": "bgp_summary.$peak_rib_out_entries",
                                "varName": "$peak_rib_out_entries"
                            }
                        ]
                    },
                    "mappingType": 2,
                    "name": "$peak_rib_out_entries",
                    "nodeType": 4,
                    "params": [],
                    "rules": null,
                    "valueType": 0
                },
                {
                    "_id": "c99f00d5-4292-4083-9a15-14a04001fbb7",
                    "children": [],
                    "command": "show routing protocol bgp summary",
                    "desc": null,
                    "isIntfKey": false,
                    "mapping": {
                        "_id": "663250fa-4957-4272-a26b-341ab31f9d45",
                        "mappingType": 2,
                        "mappingVars": [
                            {
                                "bizType": "CLI",
                                "builtIn": false,
                                "deviceType": [
                                    2130
                                ],
                                "isKey": false,
                                "parserName": "show routing protocol bgp summary [Palo Alto Firewall]",
                                "parserPath": "Built-in Files/Network Vendors/Palo Alto/Palo Alto Firewall/show routing protocol bgp summary [Palo Alto Firewall]",
                                "sourceType": 1,
                                "varFullName": "bgp_summary.$peer_type",
                                "varName": "$peer_type"
                            }
                        ]
                    },
                    "mappingType": 2,
                    "name": "$peer_type",
                    "nodeType": 4,
                    "params": [],
                    "rules": null,
                    "valueType": 0
                },
                {
                    "_id": "1a0b9d94-d5ab-4513-95f2-d2f0b4376351",
                    "children": [],
                    "command": "show routing protocol bgp summary",
                    "desc": null,
                    "isIntfKey": false,
                    "mapping": {
                        "_id": "752d18dc-ac85-4a15-a7d3-57e401c76125",
                        "mappingType": 2,
                        "mappingVars": [
                            {
                                "bizType": "CLI",
                                "builtIn": false,
                                "deviceType": [
                                    2130
                                ],
                                "isKey": false,
                                "parserName": "show routing protocol bgp summary [Palo Alto Firewall]",
                                "parserPath": "Built-in Files/Network Vendors/Palo Alto/Palo Alto Firewall/show routing protocol bgp summary [Palo Alto Firewall]",
                                "sourceType": 1,
                                "varFullName": "bgp_summary.$peer_as",
                                "varName": "$peer_as"
                            }
                        ]
                    },
                    "mappingType": 2,
                    "name": "$peer_as",
                    "nodeType": 4,
                    "params": [],
                    "rules": null,
                    "valueType": 0
                },
                {
                    "_id": "cdc607d5-3ef9-4bb3-980e-e9a236cb5f35",
                    "children": [],
                    "command": "show routing protocol bgp summary",
                    "desc": null,
                    "isIntfKey": false,
                    "mapping": {
                        "_id": "18b6b2ea-9fb1-4b4f-927b-9ce8d62db128",
                        "mappingType": 2,
                        "mappingVars": [
                            {
                                "bizType": "CLI",
                                "builtIn": false,
                                "deviceType": [
                                    2130
                                ],
                                "isKey": false,
                                "parserName": "show routing protocol bgp summary [Palo Alto Firewall]",
                                "parserPath": "Built-in Files/Network Vendors/Palo Alto/Palo Alto Firewall/show routing protocol bgp summary [Palo Alto Firewall]",
                                "sourceType": 1,
                                "varFullName": "bgp_summary.$peer_state",
                                "varName": "$peer_state"
                            }
                        ]
                    },
                    "mappingType": 2,
                    "name": "$peer_state",
                    "nodeType": 4,
                    "params": [],
                    "rules": null,
                    "valueType": 0
                },
                {
                    "_id": "9f913a1b-c582-488d-95d4-0876f9c60eb1",
                    "children": [],
                    "command": "show routing protocol bgp summary",
                    "desc": null,
                    "isIntfKey": false,
                    "mapping": {
                        "_id": "0bccbe4e-3ab9-4d29-bcbe-56b9bdc1022b",
                        "mappingType": 2,
                        "mappingVars": [
                            {
                                "bizType": "CLI",
                                "builtIn": false,
                                "deviceType": [
                                    2130
                                ],
                                "isKey": false,
                                "parserName": "show routing protocol bgp summary [Palo Alto Firewall]",
                                "parserPath": "Built-in Files/Network Vendors/Palo Alto/Palo Alto Firewall/show routing protocol bgp summary [Palo Alto Firewall]",
                                "sourceType": 1,
                                "varFullName": "bgp_summary.$peer_address",
                                "varName": "$peer_address"
                            }
                        ]
                    },
                    "mappingType": 2,
                    "name": "$peer_address",
                    "nodeType": 4,
                    "params": [],
                    "rules": null,
                    "valueType": 0
                },
                {
                    "_id": "44e2cc6d-de1d-4635-8740-1443fcf5ab64",
                    "children": [],
                    "command": "show routing protocol bgp summary",
                    "desc": null,
                    "isIntfKey": false,
                    "mapping": {
                        "_id": "25858149-78e0-42ee-90a4-ea61aab0b8ca",
                        "mappingType": 2,
                        "mappingVars": [
                            {
                                "bizType": "CLI",
                                "builtIn": false,
                                "deviceType": [
                                    2130
                                ],
                                "isKey": false,
                                "parserName": "show routing protocol bgp summary [Palo Alto Firewall]",
                                "parserPath": "Built-in Files/Network Vendors/Palo Alto/Palo Alto Firewall/show routing protocol bgp summary [Palo Alto Firewall]",
                                "sourceType": 1,
                                "varFullName": "bgp_summary.$accepted_pfx",
                                "varName": "$accepted_pfx"
                            }
                        ]
                    },
                    "mappingType": 2,
                    "name": "$accepted_pfx",
                    "nodeType": 4,
                    "params": [],
                    "rules": null,
                    "valueType": 0
                },
                {
                    "_id": "ec0ec6f6-f61f-4c94-9e50-d6cca408aeae",
                    "children": [],
                    "command": "show routing protocol bgp summary",
                    "desc": null,
                    "isIntfKey": false,
                    "mapping": {
                        "_id": "3f38b9e1-d323-46d6-a681-faecab5746c3",
                        "mappingType": 2,
                        "mappingVars": [
                            {
                                "bizType": "CLI",
                                "builtIn": false,
                                "deviceType": [
                                    2130
                                ],
                                "isKey": false,
                                "parserName": "show routing protocol bgp summary [Palo Alto Firewall]",
                                "parserPath": "Built-in Files/Network Vendors/Palo Alto/Palo Alto Firewall/show routing protocol bgp summary [Palo Alto Firewall]",
                                "sourceType": 1,
                                "varFullName": "bgp_summary.$advertised_pfx",
                                "varName": "$advertised_pfx"
                            }
                        ]
                    },
                    "mappingType": 2,
                    "name": "$advertised_pfx",
                    "nodeType": 4,
                    "params": [],
                    "rules": null,
                    "valueType": 0
                }
            ],
            "command": "show routing protocol bgp summary",
            "desc": null,
            "isIntfKey": false,
            "mapping": {
                "_id": "7cf303c5-0510-46ec-8432-d8d11832eab7",
                "mappingType": 1,
                "mappingVars": [
                    {
                        "bizType": "CLI",
                        "builtIn": false,
                        "deviceType": [
                            2130
                        ],
                        "isKey": false,
                        "parserName": "show routing protocol bgp summary [Palo Alto Firewall]",
                        "parserPath": "Built-in Files/Network Vendors/Palo Alto/Palo Alto Firewall/show routing protocol bgp summary [Palo Alto Firewall]",
                        "sourceType": 1,
                        "varFullName": "bgp_summary",
                        "varName": "bgp_summary"
                    }
                ]
            },
            "mappingType": 1,
            "name": "bgp_summary",
            "nodeType": 3,
            "params": [],
            "rules": [
                {
                    "_id": "9bc0bd1b-a060-4aad-b69e-858f4881b58d",
                    "isCustomerEnable": 0,
                    "isInitialEnable": true,
                    "ruleAlgParameter": "",
                    "ruleTypeId": -1
                }
            ],
            "valueType": 0
        },
        {
            "_id": "81ba78a2-2111-4d76-9596-67201ccfb8ec",
            "children": [],
            "command": null,
            "desc": null,
            "isIntfKey": false,
            "mapping": null,
            "mappingType": 0,
            "name": "$cli_output",
            "nodeType": 2,
            "params": null,
            "rules": null,
            "valueType": 0
        }
    ],
    "command": null,
    "desc": null,
    "isIntfKey": false,
    "mapping": null,
    "mappingType": 0,
    "nodeType": 1,
    "params": null,
    "rules": null,
    "valueType": 0
}